aiosalesforce/__init__.py
aiosalesforce/client.py
aiosalesforce/exceptions.py
aiosalesforce/py.typed
aiosalesforce/sobject.py
aiosalesforce/utils.py
aiosalesforce/auth/__init__.py
aiosalesforce/auth/base.py
aiosalesforce/auth/client_credentials_flow.py
aiosalesforce/auth/jwt_bearer_flow.py
aiosalesforce/auth/soap.py
aiosalesforce/bulk/__init__.py
aiosalesforce/bulk/v2/__init__.py
aiosalesforce/bulk/v2/_csv.py
aiosalesforce/bulk/v2/client.py
aiosalesforce/bulk/v2/ingest.py
aiosalesforce/composite/__init__.py
aiosalesforce/composite/batch.py
aiosalesforce/composite/client.py
aiosalesforce/composite/composite.py
aiosalesforce/composite/exceptions.py
aiosalesforce/events/__init__.py
aiosalesforce/events/event_bus.py
aiosalesforce/events/events.py
aiosalesforce/retries/__init__.py
aiosalesforce/retries/policy.py
aiosalesforce/retries/rules.py
aiosalesforce-0.6.2.dist-info/METADATA
aiosalesforce-0.6.2.dist-info/WHEEL
aiosalesforce-0.6.2.dist-info/licenses/LICENSE
aiosalesforce-0.6.2.dist-info/RECORD
