Metadata-Version: 2.3
Name: aiosalesforce
Version: 0.6.2
Summary: Salesforce REST API client
Project-URL: Homepage, https://github.com/georgebv/aiosalesforce
Project-URL: Documentation, https://github.com/georgebv/aiosalesforce
Project-URL: Repository, https://github.com/georgebv/aiosalesforce
Author-email: Georgii Bocharov <bocharovgeorgii@gmail.com>
License: Copyright 2024 Georgii Bocharov
License-File: LICENSE
Keywords: REST API,asyncio,salesforce
Requires-Python: >=3.11
Requires-Dist: httpx>=0.27.0
Requires-Dist: orjson>=3.9.15
Provides-Extra: jwt
Requires-Dist: pyjwt[crypto]>=2.8.0; extra == 'jwt'
